README.md
setup.py
example/__init__.py
example/sample.py
example/sample2.py
skl_utils/__init__.py
skl_utils.egg-info/PKG-INFO
skl_utils.egg-info/SOURCES.txt
skl_utils.egg-info/dependency_links.txt
skl_utils.egg-info/requires.txt
skl_utils.egg-info/top_level.txt