Metadata-Version: 2.1
Name: skl-utils
Version: 0.0.2
Summary: Scikit-Learn Ultilities
Home-page: https://github.com/sotheara-leang/skl_utils
Author: LEANG Sotheara
Author-email: leangsotheara@gmail.com
License: UNKNOWN
Keywords: scikit-learn,pandas,utilities
Platform: UNKNOWN
Classifier: Development Status :: 3 - Alpha
Classifier: Intended Audience :: Developers
Classifier: License :: OSI Approved :: MIT License
Requires-Python: >=3.5
